examples/simplebot.py
tests/__init__.py
tests/logo.py
tests/test_botlongpoll.py
tests/test_event_loop.py
tests/test_handlers.py
tests/test_http.py
tests/test_logging.py
tests/test_rules.py
tests/test_twiml.py
tests/test_validators.py
tests/test_vkmethodsbase.py
twilight_vk/__init__.py
twilight_vk/api/twilight_api.py
twilight_vk/api/routers/__init__.py
twilight_vk/api/routers/base.py
twilight_vk/api/routers/root.py
twilight_vk/components/logo.py
twilight_vk/framework/twilight_vk.py
twilight_vk/framework/api/__init__.py
twilight_vk/framework/api/routers/framework.py
twilight_vk/framework/api/routers/vk_api.py
twilight_vk/framework/exceptions/__init__.py
twilight_vk/framework/exceptions/framework.py
twilight_vk/framework/exceptions/handler.py
twilight_vk/framework/exceptions/validator.py
twilight_vk/framework/exceptions/vkapi.py
twilight_vk/framework/handlers/__init__.py
twilight_vk/framework/handlers/event_handlers.py
twilight_vk/framework/methods/__init__.py
twilight_vk/framework/methods/base.py
twilight_vk/framework/methods/groups.py
twilight_vk/framework/methods/messages.py
twilight_vk/framework/methods/users.py
twilight_vk/framework/polling/base_longpoll.py
twilight_vk/framework/polling/bots_longpoll.py
twilight_vk/framework/rules/__init__.py
twilight_vk/framework/rules/base.py
twilight_vk/framework/rules/rules.py
twilight_vk/framework/validators/event_validator.py
twilight_vk/framework/validators/http_validator.py
twilight_vk/http/async_http.py
twilight_vk/logger/__init__.py
twilight_vk/logger/darky_logger.py
twilight_vk/logger/darky_visual.py
twilight_vk/logger/formatters.py
twilight_vk/utils/config.py
twilight_vk/utils/event_loop.py
twilight_vk/utils/twiml.py
twilight_vk/utils/types/event_types.py
twilight_vk/utils/types/response.py
twilight_vk/utils/types/twi_states.py
twilight_vk-0.1.0a5.dist-info/licenses/LICENSE
twilight_vk-0.1.0a5.dist-info/METADATA
twilight_vk-0.1.0a5.dist-info/WHEEL
twilight_vk-0.1.0a5.dist-info/top_level.txt
twilight_vk-0.1.0a5.dist-info/RECORD
