Metadata-Version: 2.4
Name: twilight-vk
Version: 0.1.0a5
Summary: Асинхронная библиотека для работы с VK API, с поддержкой API эндпоинтов
Author: darky_wings
License: MIT License
Project-URL: Homepage, https://github.com/darky-bot/TwilightVK
Project-URL: Repository, https://github.com/darky-bot/TwilightVK
Project-URL: Issues, https://github.com/darky-bot/TwilightVK/issues
Classifier: Development Status :: 3 - Alpha
Classifier: Intended Audience :: Developers
Classifier: License :: OSI Approved :: MIT License
Classifier: Programming Language :: Python :: 3.12
Classifier: Programming Language :: Python :: 3.13
Classifier: Topic :: Software Development :: Libraries :: Python Modules
Classifier: Topic :: Software Development :: Libraries :: Application Frameworks
Requires-Python: >=3.12
License-File: LICENSE
Requires-Dist: aiohttp==3.12.15
Requires-Dist: fastapi==0.115.12
Requires-Dist: PyYAML==6.0.2
Requires-Dist: uvicorn==0.34.0
Provides-Extra: dev
Requires-Dist: pytest>=8.3.0; extra == "dev"
Requires-Dist: pytest-asyncio>=1.0.0; extra == "dev"
Requires-Dist: pytest-mock>=3.15.0; extra == "dev"
Requires-Dist: pytest-mypy>=1.0.0; extra == "dev"
Dynamic: license-file
